{
	"info": {
		"_postman_id": "ee4e2998-2b78-40c6-9020-cdec53be2c91",
		"name": "otus",
		"schema": "https://schema.getpostman.com/json/collection/v2.1.0/collection.json"
	},
	"item": [
		{
			"name": "http://arch.homework/otusapp/larisa/health",
			"request": {
				"method": "GET",
				"header": [],
				"body": {
					"mode": "raw",
					"raw": ""
				},
				"url": {
					"raw": "http://arch.homework/otusapp/larisa/health",
					"protocol": "http",
					"host": [
						"arch",
						"homework"
					],
					"path": [
						"otusapp",
						"larisa",
						"health"
					]
				}
			},
			"response": [
				{
					"name": "http://arch.homework/otusapp/larisa/health",
					"originalRequest": {
						"method": "GET",
						"header": [],
						"body": {
							"mode": "raw",
							"raw": ""
						},
						"url": {
							"raw": "http://arch.homework/otusapp/larisa/health",
							"protocol": "http",
							"host": [
								"arch",
								"homework"
							],
							"path": [
								"otusapp",
								"larisa",
								"health"
							]
						}
					},
					"status": "OK",
					"code": 200,
					"_postman_previewlanguage": "html",
					"header": [
						{
							"key": "Server",
							"value": "nginx/1.17.10"
						},
						{
							"key": "Date",
							"value": "Sun, 19 Jul 2020 19:28:34 GMT"
						},
						{
							"key": "Content-Type",
							"value": "text/html; charset=utf-8"
						},
						{
							"key": "Content-Length",
							"value": "16"
						},
						{
							"key": "Connection",
							"value": "keep-alive"
						}
					],
					"cookie": [],
					"body": "{\"status\": \"ok\"}"
				}
			]
		}
	]
}